goodhomepy/__init__.py
goodhomepy/client.py
goodhomepy/models.py
goodhomepy-1.1.2.dist-info/METADATA
goodhomepy-1.1.2.dist-info/WHEEL
goodhomepy-1.1.2.dist-info/top_level.txt
goodhomepy-1.1.2.dist-info/RECORD
