Metadata-Version: 2.1
Name: goodhomepy
Version: 1.1.2
Summary: Good Home API Client is a Python client for interacting with the Good Home API. This client allows you to manage authentication, refresh tokens, verify tokens, and retrieve information about users, devices, and homes via the Good Home API.
Home-page: https://github.com/biker91620/goodhomepy
Author: biker91620
Author-email: biker91620@gmail.com
